LICENSE
README.md
setup.py
geom_tools/__init__.py
geom_tools/adjacency_tools.py
geom_tools/bounding_box.py
geom_tools/mesh.py
geom_tools/normals_tools.py
geom_tools/obj_export.py
geom_tools/obj_import.py
geom_tools/rigid_alignment.py
geom_tools/transformations.py
geom_tools/utils.py
geom_tools/version.py
geom_tools.egg-info/PKG-INFO
geom_tools.egg-info/SOURCES.txt
geom_tools.egg-info/dependency_links.txt
geom_tools.egg-info/requires.txt
geom_tools.egg-info/top_level.txt
geom_tools/csrc/obj_import_cpp.cpp